{
	"miniprogramRoot": "miniprogram/",
	"cloudfunctionRoot": "cloudfunctions/",
	"setting": {
		"urlCheck": false,
		"es6": true,
		"enhance": true,
		"postcss": true,
		"preloadBackgroundData": false,
		"minified": true,
		"newFeature": true,
		"coverView": true,
		"autoAudits": false,
		"showShadowRootInWxmlPanel": true,
		"scopeDataCheck": false,
		"checkInvalidKey": true,
		"checkSiteMap": true,
		"uploadWithSourceMap": true,
		"babelSetting": {
			"ignore": [],
			"disablePlugins": [],
			"outputPath": ""
		}
	},
	"appid": "wxae0ca1be06d0da0f",
	"projectname": "VipCard",
	"libVersion": "2.8.1",
	"simulatorType": "wechat",
	"simulatorPluginLibVersion": {},
	"condition": {
		"search": {
			"current": -1,
			"list": []
		},
		"conversation": {
			"current": -1,
			"list": []
		},
		"plugin": {
			"current": -1,
			"list": []
		},
		"game": {
			"list": []
		},
		"gamePlugin": {
			"current": -1,
			"list": []
		},
		"miniprogram": {
			"current": 0,
			"list": [
				{
					"id": -1,
					"name": "db guide",
					"pathName": "pages/databaseGuide/databaseGuide",
					"query": ""
				},
				{
					"id": -1,
					"name": "pages/personal/personal",
					"pathName": "pages/personal/personal",
					"query": "",
					"scene": null
				},
				{
					"id": -1,
					"name": "pages/index/index",
					"pathName": "pages/index/index",
					"query": "",
					"scene": null
				},
				{
					"id": -1,
					"name": "pages/time/time",
					"pathName": "pages/time/time",
					"query": "",
					"scene": null
				},
				{
					"id": -1,
					"name": "pages/personal/personal",
					"pathName": "pages/personal/personal",
					"query": "",
					"scene": null
				},
				{
					"id": -1,
					"name": "pages/personal/vipCard/vipCard",
					"pathName": "pages/personal/vipCard/vipCard",
					"query": "",
					"scene": null
				},
				{
					"id": -1,
					"name": "pages/personal/vipCard/record/record",
					"pathName": "pages/personal/vipCard/record/record",
					"scene": null
				}
			]
		}
	}
}